odoo/addons/stock_move_quantity_product_uom/README.rst
odoo/addons/stock_move_quantity_product_uom/__init__.py
odoo/addons/stock_move_quantity_product_uom/__manifest__.py
odoo/addons/stock_move_quantity_product_uom/hook.py
odoo/addons/stock_move_quantity_product_uom/i18n/it.po
odoo/addons/stock_move_quantity_product_uom/i18n/pt.po
odoo/addons/stock_move_quantity_product_uom/i18n/pt_BR.po
odoo/addons/stock_move_quantity_product_uom/i18n/stock_move_quantity_product_uom.pot
odoo/addons/stock_move_quantity_product_uom/models/__init__.py
odoo/addons/stock_move_quantity_product_uom/models/stock_move.py
odoo/addons/stock_move_quantity_product_uom/readme/CONTRIBUTORS.md
odoo/addons/stock_move_quantity_product_uom/readme/DESCRIPTION.md
odoo/addons/stock_move_quantity_product_uom/readme/ROADMAP.md
odoo/addons/stock_move_quantity_product_uom/static/description/icon.png
odoo/addons/stock_move_quantity_product_uom/static/description/index.html
odoo/addons/stock_move_quantity_product_uom/tests/__init__.py
odoo/addons/stock_move_quantity_product_uom/tests/test_stock_move_quantity_product_uom.py
odoo_addon_stock_move_quantity_product_uom-18.0.1.0.2.2.dist-info/METADATA
odoo_addon_stock_move_quantity_product_uom-18.0.1.0.2.2.dist-info/WHEEL
odoo_addon_stock_move_quantity_product_uom-18.0.1.0.2.2.dist-info/top_level.txt
odoo_addon_stock_move_quantity_product_uom-18.0.1.0.2.2.dist-info/RECORD
