Metadata-Version: 2.1
Name: odoo-addon-stock_move_quantity_product_uom
Version: 18.0.1.0.2.2
Requires-Python: >=3.10
Requires-Dist: odoo==18.0.*
Summary: computes stock.move's quantity in the uom of the product.
Home-page: https://github.com/OCA/stock-logistics-workflow
License: LGPL-3
Author: ForgeFlow S.L., Odoo Community Association (OCA)
Author-email: support@odoo-community.org
Classifier: Programming Language :: Python
Classifier: Framework :: Odoo
Classifier: Framework :: Odoo :: 18.0
Classifier: License :: OSI Approved :: GNU Lesser General Public License v3 (LGPLv3)
Classifier: Development Status :: 5 - Production/Stable
